git_doc_history/__init__.py
git_doc_history/__main__.py
git_doc_history/config.py
git_doc_history/py.typed
git_doc_history-0.1.1.data/scripts/file_backups_to_doc_history
git_doc_history-0.1.1.data/scripts/git_doc_history
git_doc_history-0.1.1.dist-info/LICENSE
git_doc_history-0.1.1.dist-info/METADATA
git_doc_history-0.1.1.dist-info/WHEEL
git_doc_history-0.1.1.dist-info/top_level.txt
git_doc_history-0.1.1.dist-info/RECORD
