Metadata-Version: 2.1
Name: git-doc-history
Version: 0.1.1
Summary: copy/track files in git, and a CLI tool/library to traverse the history
Home-page: https://github.com/seanbreckenridge/git_doc_history
Author: Sean Breckenridge
Author-email: seanbrecke@gmail.com
License: MIT
Keywords: data git
Platform: UNKNOWN
Classifier: License :: OSI Approved :: MIT License
Classifier: Programming Language :: Python
Classifier: Programming Language :: Python :: 3
Classifier: Programming Language :: Python :: 3.7
Classifier: Programming Language :: Python :: 3.8
Classifier: Programming Language :: Python :: 3.9
Classifier: Programming Language :: Python :: 3.10
Requires-Python: >=3.8
License-File: LICENSE
Requires-Dist: gitpython
Requires-Dist: dateparser
Requires-Dist: click (>=8.0)
Requires-Dist: python-dotenv
Provides-Extra: testing
Requires-Dist: pytest ; extra == 'testing'
Requires-Dist: mypy ; extra == 'testing'
Requires-Dist: flake8 ; extra == 'testing'
